Workbook

Sheet Léeme
A1: Modelo económico · Oasis Pachacámac · Un espacio SAWA
A3: Versión 261018. Generado con scripts/modelo-economico.py (no editar la estructura a mano: regenerar).
A5: Cómo usarlo
A6: 1. Cambia SOLO las celdas amarillas de la hoja Parámetros. Todo lo demás son fórmulas vivas.
A7: 2. Unit economics: margen por evento según segmento, tipo de día y canal.
A8: 3. Mensual: 12 meses desde la reapertura con la rampa de ocupación de las metas (S10).
A9: 4. Equilibrio: eventos y ocupación de equilibrio, y payback del CAPEX.
A10: 5. Sensibilidad: resultado mensual con ocupación de 20% a 80% contra ticket ±20%.
A11: 6. Pauta vs planner: cuánto puede costar como máximo un cliente directo frente al 5% del planner.
A13: Advertencias
A14: • Todas las cifras son SUPUESTOS (ver docs/supuestos.md). Tarifas = tarifario de ejemplo (S24), por validar.
A15: • Costos fijos y CAPEX marcados [COMPLETAR] deben reemplazarse por cifras reales.
... A17: • No es una proyección financiera auditada; es una herramienta para decidir precios, metas y canales.

Sheet Parámetros
A1: Parámetros (celdas amarillas = supuestos editables)
A2: Montos en S/ sin IGV salvo indicación.
A4: Grupo | B4: Parámetro | C4: Valor | D4: Unidad | E4: Fuente / supuesto
A5: General | B5: IGV | C5: 0.18 | D5: % | E5: settings.igv_rate
A6: General | B6: Tipo de cambio referencial | C6: 3.75 | D6: S/ por USD | E6: settings.currency_usd_rate
A7: General | B7: Impuesto a la renta (régimen general) | C7: 0.295 | D7: % | E7: Por validar con contador
A9: Calendario | B9: Días V-S-D + feriados por mes | C9: 13.8 | D9: días/mes | E9: (52×3 + ~10 feriados) / 12
A10: Calendario | B10: Días L-J por mes | C10: 16.6 | D10: días/mes | E10: (365 − 166) / 12
A11: Calendario | B11: Días de mantenimiento por mes | C11: 1 | D11: días/mes | E11: Bloqueos de mantenimiento (se descuentan de L-J)
A13: Metas | B13: Ocupación V-S-D meses 1–3 | C13: 0.5 | D13: % | E13: S10
A14: Metas | B14: Ocupación V-S-D desde el mes 4 | C14: 0.7 | D14: % | E14: S10
A15: Metas | B15: Ocupación L-J al mes 6 (rampa lineal) | C15: 0.15 | D15: % | E15: S10
A16: Metas | B16: Factor de ticket en temporada alta (dic–mar) | C16: 1.12 | D16: × | E16: Diferencia alta/baja del tarifario de ejemplo
A18: Mezcla V-S-D | B18: Boda / social | C18: 0.5 | D18: % de eventos | E18: Supuesto; debe sumar 100%
A19: Mezcla V-S-D | B19: Corporativo | C19: 0.15 | D19: % de eventos | E19: Supuesto; debe sumar 100%
... A56: CAPEX (una vez) | B56: Lanzamiento | C56: 5000 | D56: S/ | E56: [COMPLETAR] supuesto por validar
B58: Control: mezcla V-S-D suma 100% | C58: =IF(ABS(Parámetros!$C$18+Parámetros!$C$19+Parámetros!$C$20-1)<0.001,"OK","REVISAR")
B59: Control: mezcla L-J suma 100% | C59: =IF(ABS(Parámetros!$C$21+Parámetros!$C$22+Parámetros!$C$23-1)<0.001,"OK","REVISAR")
B60: Control: canales suman 100% | C60: =IF(ABS(Parámetros!$C$32+Parámetros!$C$33+Parámetros!$C$34-1)<0.001,"OK","REVISAR")

Sheet Unit economics
A1: Unit economics por evento
A2: Margen de contribución = alquiler sin IGV − costo directo − costo del canal.
A4: Segmento | B4: Día | C4: Ticket sin IGV | D4: IGV | E4: Ticket con IGV | F4: Costo directo | G4: Contribución antes de canal | H4: Margen %
A5: Boda / social | B5: V-S-D | C5: =Parámetros!$C$25 | D5: =C5*Parámetros!$C$5 | E5: =C5+D5 | F5: =Parámetros!$C$39 | G5: =C5-F5 | H5: =IF(C5>0,G5/C5,0)
A6: Boda / social | B6: L-J | C6: =Parámetros!$C$28 | D6: =C6*Parámetros!$C$5 | E6: =C6+D6 | F6: =Parámetros!$C$39 | G6: =C6-F6 | H6: =IF(C6>0,G6/C6,0)
A7: Corporativo | B7: V-S-D | C7: =Parámetros!$C$26 | D7: =C7*Parámetros!$C$5 | E7: =C7+D7 | F7: =Parámetros!$C$39 | G7: =C7-F7 | H7: =IF(C7>0,G7/C7,0)
A8: Corporativo | B8: L-J | C8: =Parámetros!$C$29 | D8: =C8*Parámetros!$C$5 | E8: =C8+D8 | F8: =Parámetros!$C$39 | G8: =C8-F8 | H8: =IF(C8>0,G8/C8,0)
A9: Full day familiar | B9: V-S-D | C9: =Parámetros!$C$27 | D9: =C9*Parámetros!$C$5 | E9: =C9+D9 | F9: =Parámetros!$C$39 | G9: =C9-F9 | H9: =IF(C9>0,G9/C9,0)
A10: Full day familiar | B10: L-J | C10: =Parámetros!$C$30 | D10: =C10*Parámetros!$C$5 | E10: =C10+D10 | F10: =Parámetros!$C$39 | G10: =C10-F10 | H10: =IF(C10>0,G10/C10,0)
A12: Estado estable (desde el mes 6)
A13: Eventos V-S-D por mes | C13: =Parámetros!$C$9*Parámetros!$C$14
A14: Eventos L-J por mes | C14: =(Parámetros!$C$10-Parámetros!$C$11)*Parámetros!$C$15
A15: Eventos totales por mes | C15: =C13+C14
A16: Ticket promedio V-S-D | C16: =Parámetros!$C$18*Parámetros!$C$25+Parámetros!$C$19*Parámetros!$C$26+Parámetros!$C$20*Parámetros!$C$27
A17: Ticket promedio L-J | C17: =Parámetros!$C$21*Parámetros!$C$28+Parámetros!$C$22*Parámetros!$C$29+Parámetros!$C$23*Parámetros!$C$30
A18: Ticket promedio ponderado | C18: =IF(C15>0,(C13*C16+C14*C17)/C15,0)
A19: Eventos directos por mes | C19: =C15*Parámetros!$C$33
A20: CAC directo (pauta / eventos directos) | C20: =IF(C19>0,Parámetros!$C$36/C19,0)
A22: Canal | C22: Ticket promedio | D22: Costo del canal | E22: Costo directo | F22: Contribución | G22: Margen % | H22: % de eventos
A23: Planner (5% comisión) | C23: ='Unit economics'!$C$18 | D23: =C23*Parámetros!$C$35 | E23: =Parámetros!$C$39 | F23: =C23-D23-E23 | G23: =IF(C23>0,F23/C23,0) | H23: =Parámetros!$C$32
A24: Directo (pauta, CAC) | C24: ='Unit economics'!$C$18 | D24: ='Unit economics'!$C$20 | E24: =Parámetros!$C$39 | F24: =C24-D24-E24 | G24: =IF(C24>0,F24/C24,0) | H24: =Parámetros!$C$33
A25: Referido / orgánico | C25: ='Unit economics'!$C$18 | D25: =0 | E25: =Parámetros!$C$39 | F25: =C25-D25-E25 | G25: =IF(C25>0,F25/C25,0) | H25: =Parámetros!$C$34
A26: Promedio ponderado por canal | F26: =SUMPRODUCT(F23:F25,H23:H25)

Sheet Mensual
A1: Proyección mensual (12 meses desde la reapertura)
A2: Comisiones solo sobre eventos vía planner. Pauta como costo fijo mensual.
A4: Mes | B4: N.º | C4: Temporada | D4: Ocup. V-S-D | E4: Ocup. L-J | F4: Eventos V-S-D | G4: Eventos L-J | H4: Eventos | I4: Ingreso sin IGV | J4: IGV (informativo) | K4: Comisiones | L4: Costos directos | M4: Pauta | N4: Contribución | O4: OPEX fijo | P4: EBITDA | Q4: Acumulado vs CAPEX
A5: dic-26 | B5: 1 | C5: Alta | D5: =IF(B5<=3,Parámetros!$C$13,Parámetros!$C$14) | E5: =ROUND(Parámetros!$C$15*MIN(1,B5/6),3) | F5: =Parámetros!$C$9*D5 | G5: =(Parámetros!$C$10-Parámetros!$C$11)*E5 | H5: =F5+G5 | I5: =(F5*'Unit economics'!$C$16+G5*'Unit economics'!$C$17)*IF(C5="Alta",Parámetros!$C$16,1) | J5: =I5*Parámetros!$C$5 | K5: =I5*Parámetros!$C$32*Parámetros!$C$35 | L5: =H5*Parámetros!$C$39 | M5: =Parámetros!$C$36 | N5: =I5-K5-L5-M5 | O5: =Parámetros!$C$41+Parámetros!$C$42+Parámetros!$C$43+Parámetros!$C$44+Parámetros!$C$45+Parámetros!$C$46+Parámetros!$C$47+Parámetros!$C$48+Parámetros!$C$49+Parámetros!$C$50 | P5: =N5-O5 | Q5: =-(Parámetros!$C$52+Parámetros!$C$53+Parámetros!$C$54+Parámetros!$C$55+Parámetros!$C$56)+P5
A6: ene-27 | B6: 2 | C6: Alta | D6: =IF(B6<=3,Parámetros!$C$13,Parámetros!$C$14) | E6: =ROUND(Parámetros!$C$15*MIN(1,B6/6),3) | F6: =Parámetros!$C$9*D6 | G6: =(Parámetros!$C$10-Parámetros!$C$11)*E6 | H6: =F6+G6 | I6: =(F6*'Unit economics'!$C$16+G6*'Unit economics'!$C$17)*IF(C6="Alta",Parámetros!$C$16,1) | J6: =I6*Parámetros!$C$5 | K6: =I6*Parámetros!$C$32*Parámetros!$C$35 | L6: =H6*Parámetros!$C$39 | M6: =Parámetros!$C$36 | N6: =I6-K6-L6-M6 | O6: =Parámetros!$C$41+Parámetros!$C$42+Parámetros!$C$43+Parámetros!$C$44+Parámetros!$C$45+Parámetros!$C$46+Parámetros!$C$47+Parámetros!$C$48+Parámetros!$C$49+Parámetros!$C$50 | P6: =N6-O6 | Q6: =Q5+P6
A7: feb-27 | B7: 3 | C7: Alta | D7: =IF(B7<=3,Parámetros!$C$13,Parámetros!$C$14) | E7: =ROUND(Parámetros!$C$15*MIN(1,B7/6),3) | F7: =Parámetros!$C$9*D7 | G7: =(Parámetros!$C$10-Parámetros!$C$11)*E7 | H7: =F7+G7 | I7: =(F7*'Unit economics'!$C$16+G7*'Unit economics'!$C$17)*IF(C7="Alta",Parámetros!$C$16,1) | J7: =I7*Parámetros!$C$5 | K7: =I7*Parámetros!$C$32*Parámetros!$C$35 | L7: =H7*Parámetros!$C$39 | M7: =Parámetros!$C$36 | N7: =I7-K7-L7-M7 | O7: =Parámetros!$C$41+Parámetros!$C$42+Parámetros!$C$43+Parámetros!$C$44+Parámetros!$C$45+Parámetros!$C$46+Parámetros!$C$47+Parámetros!$C$48+Parámetros!$C$49+Parámetros!$C$50 | P7: =N7-O7 | Q7: =Q6+P7
A8: mar-27 | B8: 4 | C8: Alta | D8: =IF(B8<=3,Parámetros!$C$13,Parámetros!$C$14) | E8: =ROUND(Parámetros!$C$15*MIN(1,B8/6),3) | F8: =Parámetros!$C$9*D8 | G8: =(Parámetros!$C$10-Parámetros!$C$11)*E8 | H8: =F8+G8 | I8: =(F8*'Unit economics'!$C$16+G8*'Unit economics'!$C$17)*IF(C8="Alta",Parámetros!$C$16,1) | J8: =I8*Parámetros!$C$5 | K8: =I8*Parámetros!$C$32*Parámetros!$C$35 | L8: =H8*Parámetros!$C$39 | M8: =Parámetros!$C$36 | N8: =I8-K8-L8-M8 | O8: =Parámetros!$C$41+Parámetros!$C$42+Parámetros!$C$43+Parámetros!$C$44+Parámetros!$C$45+Parámetros!$C$46+Parámetros!$C$47+Parámetros!$C$48+Parámetros!$C$49+Parámetros!$C$50 | P8: =N8-O8 | Q8: =Q7+P8
A9: abr-27 | B9: 5 | C9: Baja | D9: =IF(B9<=3,Parámetros!$C$13,Parámetros!$C$14) | E9: =ROUND(Parámetros!$C$15*MIN(1,B9/6),3) | F9: =Parámetros!$C$9*D9 | G9: =(Parámetros!$C$10-Parámetros!$C$11)*E9 | H9: =F9+G9 | I9: =(F9*'Unit economics'!$C$16+G9*'Unit economics'!$C$17)*IF(C9="Alta",Parámetros!$C$16,1) | J9: =I9*Parámetros!$C$5 | K9: =I9*Parámetros!$C$32*Parámetros!$C$35 | L9: =H9*Parámetros!$C$39 | M9: =Parámetros!$C$36 | N9: =I9-K9-L9-M9 | O9: =Parámetros!$C$41+Parámetros!$C$42+Parámetros!$C$43+Parámetros!$C$44+Parámetros!$C$45+Parámetros!$C$46+Parámetros!$C$47+Parámetros!$C$48+Parámetros!$C$49+Parámetros!$C$50 | P9: =N9-O9 | Q9: =Q8+P9
A10: may-27 | B10: 6 | C10: Baja | D10: =IF(B10<=3,Parámetros!$C$13,Parámetros!$C$14) | E10: =ROUND(Parámetros!$C$15*MIN(1,B10/6),3) | F10: =Parámetros!$C$9*D10 | G10: =(Parámetros!$C$10-Parámetros!$C$11)*E10 | H10: =F10+G10 | I10: =(F10*'Unit economics'!$C$16+G10*'Unit economics'!$C$17)*IF(C10="Alta",Parámetros!$C$16,1) | J10: =I10*Parámetros!$C$5 | K10: =I10*Parámetros!$C$32*Parámetros!$C$35 | L10: =H10*Parámetros!$C$39 | M10: =Parámetros!$C$36 | N10: =I10-K10-L10-M10 | O10: =Parámetros!$C$41+Parámetros!$C$42+Parámetros!$C$43+Parámetros!$C$44+Parámetros!$C$45+Parámetros!$C$46+Parámetros!$C$47+Parámetros!$C$48+Parámetros!$C$49+Parámetros!$C$50 | P10: =N10-O10 | Q10: =Q9+P10
A11: jun-27 | B11: 7 | C11: Baja | D11: =IF(B11<=3,Parámetros!$C$13,Parámetros!$C$14) | E11: =ROUND(Parámetros!$C$15*MIN(1,B11/6),3) | F11: =Parámetros!$C$9*D11 | G11: =(Parámetros!$C$10-Parámetros!$C$11)*E11 | H11: =F11+G11 | I11: =(F11*'Unit economics'!$C$16+G11*'Unit economics'!$C$17)*IF(C11="Alta",Parámetros!$C$16,1) | J11: =I11*Parámetros!$C$5 | K11: =I11*Parámetros!$C$32*Parámetros!$C$35 | L11: =H11*Parámetros!$C$39 | M11: =Parámetros!$C$36 | N11: =I11-K11-L11-M11 | O11: =Parámetros!$C$41+Parámetros!$C$42+Parámetros!$C$43+Parámetros!$C$44+Parámetros!$C$45+Parámetros!$C$46+Parámetros!$C$47+Parámetros!$C$48+Parámetros!$C$49+Parámetros!$C$50 | P11: =N11-O11 | Q11: =Q10+P11
A12: jul-27 | B12: 8 | C12: Baja | D12: =IF(B12<=3,Parámetros!$C$13,Parámetros!$C$14) | E12: =ROUND(Parámetros!$C$15*MIN(1,B12/6),3) | F12: =Parámetros!$C$9*D12 | G12: =(Parámetros!$C$10-Parámetros!$C$11)*E12 | H12: =F12+G12 | I12: =(F12*'Unit economics'!$C$16+G12*'Unit economics'!$C$17)*IF(C12="Alta",Parámetros!$C$16,1) | J12: =I12*Parámetros!$C$5 | K12: =I12*Parámetros!$C$32*Parámetros!$C$35 | L12: =H12*Parámetros!$C$39 | M12: =Parámetros!$C$36 | N12: =I12-K12-L12-M12 | O12: =Parámetros!$C$41+Parámetros!$C$42+Parámetros!$C$43+Parámetros!$C$44+Parámetros!$C$45+Parámetros!$C$46+Parámetros!$C$47+Parámetros!$C$48+Parámetros!$C$49+Parámetros!$C$50 | P12: =N12-O12 | Q12: =Q11+P12
A13: ago-27 | B13: 9 | C13: Baja | D13: =IF(B13<=3,Parámetros!$C$13,Parámetros!$C$14) | E13: =ROUND(Parámetros!$C$15*MIN(1,B13/6),3) | F13: =Parámetros!$C$9*D13 | G13: =(Parámetros!$C$10-Parámetros!$C$11)*E13 | H13: =F13+G13 | I13: =(F13*'Unit economics'!$C$16+G13*'Unit economics'!$C$17)*IF(C13="Alta",Parámetros!$C$16,1) | J13: =I13*Parámetros!$C$5 | K13: =I13*Parámetros!$C$32*Parámetros!$C$35 | L13: =H13*Parámetros!$C$39 | M13: =Parámetros!$C$36 | N13: =I13-K13-L13-M13 | O13: =Parámetros!$C$41+Parámetros!$C$42+Parámetros!$C$43+Parámetros!$C$44+Parámetros!$C$45+Parámetros!$C$46+Parámetros!$C$47+Parámetros!$C$48+Parámetros!$C$49+Parámetros!$C$50 | P13: =N13-O13 | Q13: =Q12+P13
A14: set-27 | B14: 10 | C14: Baja | D14: =IF(B14<=3,Parámetros!$C$13,Parámetros!$C$14) | E14: =ROUND(Parámetros!$C$15*MIN(1,B14/6),3) | F14: =Parámetros!$C$9*D14 | G14: =(Parámetros!$C$10-Parámetros!$C$11)*E14 | H14: =F14+G14 | I14: =(F14*'Unit economics'!$C$16+G14*'Unit economics'!$C$17)*IF(C14="Alta",Parámetros!$C$16,1) | J14: =I14*Parámetros!$C$5 | K14: =I14*Parámetros!$C$32*Parámetros!$C$35 | L14: =H14*Parámetros!$C$39 | M14: =Parámetros!$C$36 | N14: =I14-K14-L14-M14 | O14: =Parámetros!$C$41+Parámetros!$C$42+Parámetros!$C$43+Parámetros!$C$44+Parámetros!$C$45+Parámetros!$C$46+Parámetros!$C$47+Parámetros!$C$48+Parámetros!$C$49+Parámetros!$C$50 | P14: =N14-O14 | Q14: =Q13+P14
A15: oct-27 | B15: 11 | C15: Baja | D15: =IF(B15<=3,Parámetros!$C$13,Parámetros!$C$14) | E15: =ROUND(Parámetros!$C$15*MIN(1,B15/6),3) | F15: =Parámetros!$C$9*D15 | G15: =(Parámetros!$C$10-Parámetros!$C$11)*E15 | H15: =F15+G15 | I15: =(F15*'Unit economics'!$C$16+G15*'Unit economics'!$C$17)*IF(C15="Alta",Parámetros!$C$16,1) | J15: =I15*Parámetros!$C$5 | K15: =I15*Parámetros!$C$32*Parámetros!$C$35 | L15: =H15*Parámetros!$C$39 | M15: =Parámetros!$C$36 | N15: =I15-K15-L15-M15 | O15: =Parámetros!$C$41+Parámetros!$C$42+Parámetros!$C$43+Parámetros!$C$44+Parámetros!$C$45+Parámetros!$C$46+Parámetros!$C$47+Parámetros!$C$48+Parámetros!$C$49+Parámetros!$C$50 | P15: =N15-O15 | Q15: =Q14+P15
A16: nov-27 | B16: 12 | C16: Baja | D16: =IF(B16<=3,Parámetros!$C$13,Parámetros!$C$14) | E16: =ROUND(Parámetros!$C$15*MIN(1,B16/6),3) | F16: =Parámetros!$C$9*D16 | G16: =(Parámetros!$C$10-Parámetros!$C$11)*E16 | H16: =F16+G16 | I16: =(F16*'Unit economics'!$C$16+G16*'Unit economics'!$C$17)*IF(C16="Alta",Parámetros!$C$16,1) | J16: =I16*Parámetros!$C$5 | K16: =I16*Parámetros!$C$32*Parámetros!$C$35 | L16: =H16*Parámetros!$C$39 | M16: =Parámetros!$C$36 | N16: =I16-K16-L16-M16 | O16: =Parámetros!$C$41+Parámetros!$C$42+Parámetros!$C$43+Parámetros!$C$44+Parámetros!$C$45+Parámetros!$C$46+Parámetros!$C$47+Parámetros!$C$48+Parámetros!$C$49+Parámetros!$C$50 | P16: =N16-O16 | Q16: =Q15+P16
A17: Total año | F17: =SUM(F5:F16) | G17: =SUM(G5:G16) | H17: =SUM(H5:H16) | I17: =SUM(I5:I16) | J17: =SUM(J5:J16) | K17: =SUM(K5:K16) | L17: =SUM(L5:L16) | M17: =SUM(M5:M16) | ... P17: =SUM(P5:P16)
A19: Mes de payback (dentro del año) | F19: =IFERROR(INDEX(A5:A16,MATCH(TRUE,INDEX(Q5:Q16>=0,0),0)),"Después del mes 12")

Sheet Equilibrio
A1: Punto de equilibrio y payback (estado estable)
A4: Indicador | B4: Valor | C4: Cómo se calcula
A5: Ticket promedio ponderado (sin IGV) | B5: ='Unit economics'!$C$18 | C5: Unit economics
A6: Contribución por evento (promedio de canales, sin pauta) | B6: =B5-Parámetros!$C$39-B5*Parámetros!$C$32*Parámetros!$C$35 | C6: Ticket − costo directo − comisión media
A7: Costos fijos mensuales (OPEX + pauta) | B7: =Parámetros!$C$41+Parámetros!$C$42+Parámetros!$C$43+Parámetros!$C$44+Parámetros!$C$45+Parámetros!$C$46+Parámetros!$C$47+Parámetros!$C$48+Parámetros!$C$49+Parámetros!$C$50+Parámetros!$C$36 | C7: Parámetros
A8: Eventos de equilibrio por mes | B8: =IF(B6>0,B7/B6,0) | C8: Costos fijos / contribución por evento
A9: Días disponibles por mes | B9: =Parámetros!$C$9+Parámetros!$C$10-Parámetros!$C$11 | C9: V-S-D + L-J − mantenimiento
A10: Ocupación de equilibrio | B10: =IF(B9>0,B8/B9,0) | C10: Eventos de equilibrio / días disponibles
A11: Eventos por mes en meta (estado estable) | B11: ='Unit economics'!$C$15 | C11: Metas S10
A12: EBITDA mensual en meta | B12: =B11*B6-B7 | C12: Eventos × contribución − fijos
A13: CAPEX total | B13: =Parámetros!$C$52+Parámetros!$C$53+Parámetros!$C$54+Parámetros!$C$55+Parámetros!$C$56 | C13: Parámetros
A14: Payback del CAPEX (meses en estado estable) | B14: =IF(B12>0,B13/B12,"No recupera") | C14: CAPEX / EBITDA mensual
A15: Ingreso neto por día disponible en meta | B15: =IF(B9>0,(B11*B5-B11*B5*Parámetros!$C$32*Parámetros!$C$35-B11*Parámetros!$C$39)/B9,0) | C15: KPI del dashboard

Sheet Sensibilidad
A1: Sensibilidad: EBITDA mensual (S/) según ocupación total y ticket
A2: Ocupación sobre todos los días disponibles; ticket = promedio ponderado × (1 + variación).
A4: Ocupación ↓ / Ticket → | B4: -0.2 | C4: -0.1 | D4: 0 | E4: 0.1 | F4: 0.2
A5: 0.2 | B5: =$A5*Equilibrio!$B$9*(('Unit economics'!$C$18*(1+B$4))-Parámetros!$C$39-('Unit economics'!$C$18*(1+B$4))*Parámetros!$C$32*Parámetros!$C$35)-Equilibrio!$B$7 | C5: =$A5*Equilibrio!$B$9*(('Unit economics'!$C$18*(1+C$4))-Parámetros!$C$39-('Unit economics'!$C$18*(1+C$4))*Parámetros!$C$32*Parámetros!$C$35)-Equilibrio!$B$7 | D5: =$A5*Equilibrio!$B$9*(('Unit economics'!$C$18*(1+D$4))-Parámetros!$C$39-('Unit economics'!$C$18*(1+D$4))*Parámetros!$C$32*Parámetros!$C$35)-Equilibrio!$B$7 | E5: =$A5*Equilibrio!$B$9*(('Unit economics'!$C$18*(1+E$4))-Parámetros!$C$39-('Unit economics'!$C$18*(1+E$4))*Parámetros!$C$32*Parámetros!$C$35)-Equilibrio!$B$7 | F5: =$A5*Equilibrio!$B$9*(('Unit economics'!$C$18*(1+F$4))-Parámetros!$C$39-('Unit economics'!$C$18*(1+F$4))*Parámetros!$C$32*Parámetros!$C$35)-Equilibrio!$B$7
A6: 0.3 | B6: =$A6*Equilibrio!$B$9*(('Unit economics'!$C$18*(1+B$4))-Parámetros!$C$39-('Unit economics'!$C$18*(1+B$4))*Parámetros!$C$32*Parámetros!$C$35)-Equilibrio!$B$7 | C6: =$A6*Equilibrio!$B$9*(('Unit economics'!$C$18*(1+C$4))-Parámetros!$C$39-('Unit economics'!$C$18*(1+C$4))*Parámetros!$C$32*Parámetros!$C$35)-Equilibrio!$B$7 | D6: =$A6*Equilibrio!$B$9*(('Unit economics'!$C$18*(1+D$4))-Parámetros!$C$39-('Unit economics'!$C$18*(1+D$4))*Parámetros!$C$32*Parámetros!$C$35)-Equilibrio!$B$7 | E6: =$A6*Equilibrio!$B$9*(('Unit economics'!$C$18*(1+E$4))-Parámetros!$C$39-('Unit economics'!$C$18*(1+E$4))*Parámetros!$C$32*Parámetros!$C$35)-Equilibrio!$B$7 | F6: =$A6*Equilibrio!$B$9*(('Unit economics'!$C$18*(1+F$4))-Parámetros!$C$39-('Unit economics'!$C$18*(1+F$4))*Parámetros!$C$32*Parámetros!$C$35)-Equilibrio!$B$7
A7: 0.4 | B7: =$A7*Equilibrio!$B$9*(('Unit economics'!$C$18*(1+B$4))-Parámetros!$C$39-('Unit economics'!$C$18*(1+B$4))*Parámetros!$C$32*Parámetros!$C$35)-Equilibrio!$B$7 | C7: =$A7*Equilibrio!$B$9*(('Unit economics'!$C$18*(1+C$4))-Parámetros!$C$39-('Unit economics'!$C$18*(1+C$4))*Parámetros!$C$32*Parámetros!$C$35)-Equilibrio!$B$7 | D7: =$A7*Equilibrio!$B$9*(('Unit economics'!$C$18*(1+D$4))-Parámetros!$C$39-('Unit economics'!$C$18*(1+D$4))*Parámetros!$C$32*Parámetros!$C$35)-Equilibrio!$B$7 | E7: =$A7*Equilibrio!$B$9*(('Unit economics'!$C$18*(1+E$4))-Parámetros!$C$39-('Unit economics'!$C$18*(1+E$4))*Parámetros!$C$32*Parámetros!$C$35)-Equilibrio!$B$7 | F7: =$A7*Equilibrio!$B$9*(('Unit economics'!$C$18*(1+F$4))-Parámetros!$C$39-('Unit economics'!$C$18*(1+F$4))*Parámetros!$C$32*Parámetros!$C$35)-Equilibrio!$B$7
A8: 0.5 | B8: =$A8*Equilibrio!$B$9*(('Unit economics'!$C$18*(1+B$4))-Parámetros!$C$39-('Unit economics'!$C$18*(1+B$4))*Parámetros!$C$32*Parámetros!$C$35)-Equilibrio!$B$7 | C8: =$A8*Equilibrio!$B$9*(('Unit economics'!$C$18*(1+C$4))-Parámetros!$C$39-('Unit economics'!$C$18*(1+C$4))*Parámetros!$C$32*Parámetros!$C$35)-Equilibrio!$B$7 | D8: =$A8*Equilibrio!$B$9*(('Unit economics'!$C$18*(1+D$4))-Parámetros!$C$39-('Unit economics'!$C$18*(1+D$4))*Parámetros!$C$32*Parámetros!$C$35)-Equilibrio!$B$7 | E8: =$A8*Equilibrio!$B$9*(('Unit economics'!$C$18*(1+E$4))-Parámetros!$C$39-('Unit economics'!$C$18*(1+E$4))*Parámetros!$C$32*Parámetros!$C$35)-Equilibrio!$B$7 | F8: =$A8*Equilibrio!$B$9*(('Unit economics'!$C$18*(1+F$4))-Parámetros!$C$39-('Unit economics'!$C$18*(1+F$4))*Parámetros!$C$32*Parámetros!$C$35)-Equilibrio!$B$7
A9: 0.6 | B9: =$A9*Equilibrio!$B$9*(('Unit economics'!$C$18*(1+B$4))-Parámetros!$C$39-('Unit economics'!$C$18*(1+B$4))*Parámetros!$C$32*Parámetros!$C$35)-Equilibrio!$B$7 | C9: =$A9*Equilibrio!$B$9*(('Unit economics'!$C$18*(1+C$4))-Parámetros!$C$39-('Unit economics'!$C$18*(1+C$4))*Parámetros!$C$32*Parámetros!$C$35)-Equilibrio!$B$7 | D9: =$A9*Equilibrio!$B$9*(('Unit economics'!$C$18*(1+D$4))-Parámetros!$C$39-('Unit economics'!$C$18*(1+D$4))*Parámetros!$C$32*Parámetros!$C$35)-Equilibrio!$B$7 | E9: =$A9*Equilibrio!$B$9*(('Unit economics'!$C$18*(1+E$4))-Parámetros!$C$39-('Unit economics'!$C$18*(1+E$4))*Parámetros!$C$32*Parámetros!$C$35)-Equilibrio!$B$7 | F9: =$A9*Equilibrio!$B$9*(('Unit economics'!$C$18*(1+F$4))-Parámetros!$C$39-('Unit economics'!$C$18*(1+F$4))*Parámetros!$C$32*Parámetros!$C$35)-Equilibrio!$B$7
A10: 0.7 | B10: =$A10*Equilibrio!$B$9*(('Unit economics'!$C$18*(1+B$4))-Parámetros!$C$39-('Unit economics'!$C$18*(1+B$4))*Parámetros!$C$32*Parámetros!$C$35)-Equilibrio!$B$7 | C10: =$A10*Equilibrio!$B$9*(('Unit economics'!$C$18*(1+C$4))-Parámetros!$C$39-('Unit economics'!$C$18*(1+C$4))*Parámetros!$C$32*Parámetros!$C$35)-Equilibrio!$B$7 | D10: =$A10*Equilibrio!$B$9*(('Unit economics'!$C$18*(1+D$4))-Parámetros!$C$39-('Unit economics'!$C$18*(1+D$4))*Parámetros!$C$32*Parámetros!$C$35)-Equilibrio!$B$7 | E10: =$A10*Equilibrio!$B$9*(('Unit economics'!$C$18*(1+E$4))-Parámetros!$C$39-('Unit economics'!$C$18*(1+E$4))*Parámetros!$C$32*Parámetros!$C$35)-Equilibrio!$B$7 | F10: =$A10*Equilibrio!$B$9*(('Unit economics'!$C$18*(1+F$4))-Parámetros!$C$39-('Unit economics'!$C$18*(1+F$4))*Parámetros!$C$32*Parámetros!$C$35)-Equilibrio!$B$7
A11: 0.8 | B11: =$A11*Equilibrio!$B$9*(('Unit economics'!$C$18*(1+B$4))-Parámetros!$C$39-('Unit economics'!$C$18*(1+B$4))*Parámetros!$C$32*Parámetros!$C$35)-Equilibrio!$B$7 | C11: =$A11*Equilibrio!$B$9*(('Unit economics'!$C$18*(1+C$4))-Parámetros!$C$39-('Unit economics'!$C$18*(1+C$4))*Parámetros!$C$32*Parámetros!$C$35)-Equilibrio!$B$7 | D11: =$A11*Equilibrio!$B$9*(('Unit economics'!$C$18*(1+D$4))-Parámetros!$C$39-('Unit economics'!$C$18*(1+D$4))*Parámetros!$C$32*Parámetros!$C$35)-Equilibrio!$B$7 | E11: =$A11*Equilibrio!$B$9*(('Unit economics'!$C$18*(1+E$4))-Parámetros!$C$39-('Unit economics'!$C$18*(1+E$4))*Parámetros!$C$32*Parámetros!$C$35)-Equilibrio!$B$7 | F11: =$A11*Equilibrio!$B$9*(('Unit economics'!$C$18*(1+F$4))-Parámetros!$C$39-('Unit economics'!$C$18*(1+F$4))*Parámetros!$C$32*Parámetros!$C$35)-Equilibrio!$B$7

Sheet Pauta vs planner
A1: Punto de equilibrio entre pauta y planner
A2: Si el CAC directo supera la comisión del planner, cada evento por pauta deja menos margen que uno por planner.
A4: Indicador | B4: Valor | C4: Nota
A5: Ticket promedio ponderado (sin IGV) | B5: ='Unit economics'!$C$18
A6: Comisión del planner por evento (= CAC máximo tolerable) | B6: =B5*Parámetros!$C$35 | C6: Equilibrio: pagar más que esto por cliente directo no conviene
A7: CAC directo actual (supuesto) | B7: ='Unit economics'!$C$20 | C7: Pauta mensual / eventos directos
A8: Veredicto | B8: =IF(B7<=B6,"La pauta cuesta menos que la comisión: OK","La pauta cuesta MÁS que la comisión: revisar campañas") | C8: Mismo criterio que la alerta del dashboard
A9: CPL máximo con la conversión supuesta | B9: =B6*Parámetros!$C$37 | C9: CAC máximo × conversión lead → evento
A10: Eventos directos necesarios para justificar la pauta | B10: =IF(B6>0,Parámetros!$C$36/B6,0) | C10: Pauta / CAC máximo
A12: CPL máximo según la conversión lead → evento
A13: 0.02 | B13: =$B$6*A13
A14: 0.04 | B14: =$B$6*A14
A15: 0.06 | B15: =$B$6*A15
A16: 0.08 | B16: =$B$6*A16
A17: 0.1 | B17: =$B$6*A17
A18: 0.15 | B18: =$B$6*A18
